auto_android/android_bot.py
auto_android-0.2.dist-info/LICENSE
auto_android-0.2.dist-info/METADATA
auto_android-0.2.dist-info/WHEEL
auto_android-0.2.dist-info/top_level.txt
auto_android-0.2.dist-info/RECORD
