Metadata-Version: 2.1
Name: auto-android
Version: 0.2
License-File: LICENSE
Requires-Dist: adbutils (==1.2.7)
Requires-Dist: apkutils2 (==1.0.0)
Requires-Dist: cached-property (==1.5.2)
Requires-Dist: certifi (==2022.12.7)
Requires-Dist: charset-normalizer (==3.0.1)
Requires-Dist: cigam (==0.0.3)
Requires-Dist: decorator (==5.1.1)
Requires-Dist: Deprecated (==1.2.13)
Requires-Dist: deprecation (==2.1.0)
Requires-Dist: filelock (==3.9.0)
Requires-Dist: idna (==3.4)
Requires-Dist: imutils (==0.5.4)
Requires-Dist: logzero (==1.7.0)
Requires-Dist: lxml (==4.9.2)
Requires-Dist: numpy (==1.24.2)
Requires-Dist: opencv-python (==4.7.0.68)
Requires-Dist: packaging (==20.9)
Requires-Dist: pandas (==1.5.3)
Requires-Dist: Pillow (==9.4.0)
Requires-Dist: progress (==1.6)
Requires-Dist: py (==1.11.0)
Requires-Dist: pyelftools (==0.29)
Requires-Dist: pyparsing (==3.0.9)
Requires-Dist: python-dateutil (==2.8.2)
Requires-Dist: pytz (==2022.7.1)
Requires-Dist: requests (==2.28.2)
Requires-Dist: retry (==0.9.2)
Requires-Dist: six (==1.16.0)
Requires-Dist: uiautomator2 (==2.16.22)
Requires-Dist: urllib3 (==1.26.14)
Requires-Dist: whichcraft (==0.6.1)
Requires-Dist: wrapt (==1.14.1)
Requires-Dist: xmltodict (==0.13.0)
